{
    "sheet3_prefs": [
        {
            "Trip Name": "Trip 1",
            "Preference Rating": 1
        },
        {
            "Trip Name": "Trip 2",
            "Preference Rating": 0
        },
        {
            "Trip Name": "Trip 3",
            "Preference Rating": 4
        },
        {
            "Trip Name": "Trip 4",
            "Preference Rating": 5
        },
        {
            "Trip Name": "Trip 5",
            "Preference Rating": 5
        },
        {
            "Trip Name": "Trip 6",
            "Preference Rating": 1
        },
        {
            "Trip Name": "Trip 7",
            "Preference Rating": 4
        },
        {
            "Trip Name": "Trip 8",
            "Preference Rating": 5
        },
        {
            "Trip Name": "Trip 9",
            "Preference Rating": 3
        },
        {
            "Trip Name": "Trip 10",
            "Preference Rating": 1
        },
        {
            "Trip Name": "Trip 11",
            "Preference Rating": 4
        },
        {
            "Trip Name": "Trip 12",
            "Preference Rating": 5
        },
        {
            "Trip Name": "Trip 13",
            "Preference Rating": 0
        },
        {
            "Trip Name": "Trip 14",
            "Preference Rating": 3
        },
        {
            "Trip Name": "Trip 15",
            "Preference Rating": 0
        },
        {
            "Trip Name": "Trip 16",
            "Preference Rating": 4
        },
        {
            "Trip Name": "Trip 17",
            "Preference Rating": 2
        },
        {
            "Trip Name": "Trip 18",
            "Preference Rating": 2
        },
        {
            "Trip Name": "Trip 19",
            "Preference Rating": 1
        },
        {
            "Trip Name": "Trip 20",
            "Preference Rating": 3
        },
        {
            "Trip Name": "Trip 21",
            "Preference Rating": 5
        },
        {
            "Trip Name": "Trip 22",
            "Preference Rating": 2
        },
        {
            "Trip Name": "Trip 23",
            "Preference Rating": 1
        },
        {
            "Trip Name": "Trip 24",
            "Preference Rating": 4
        },
        {
            "Trip Name": "Trip 25",
            "Preference Rating": 5
        },
        {
            "Trip Name": "Trip 26",
            "Preference Rating": 0
        },
        {
            "Trip Name": "Trip 27",
            "Preference Rating": 1
        },
        {
            "Trip Name": "Trip 28",
            "Preference Rating": 3
        },
        {
            "Trip Name": "Trip 29",
            "Preference Rating": 3
        },
        {
            "Trip Name": "Trip 30",
            "Preference Rating": 4
        },
        {
            "Trip Name": "Trip 31",
            "Preference Rating": 4
        },
        {
            "Trip Name": "Trip 32",
            "Preference Rating": 0
        },
        {
            "Trip Name": "Trip 33",
            "Preference Rating": 1
        },
        {
            "Trip Name": "Trip 34",
            "Preference Rating": 1
        },
        {
            "Trip Name": "Trip 35",
            "Preference Rating": 3
        },
        {
            "Trip Name": "Trip 36",
            "Preference Rating": 4
        },
        {
            "Trip Name": "Trip 37",
            "Preference Rating": 1
        },
        {
            "Trip Name": "Trip 38",
            "Preference Rating": 0
        },
        {
            "Trip Name": "Trip 39",
            "Preference Rating": 4
        },
        {
            "Trip Name": "Trip 40",
            "Preference Rating": 2
        },
        {
            "Trip Name": "Trip 41",
            "Preference Rating": 1
        },
        {
            "Trip Name": "Trip 42",
            "Preference Rating": 2
        },
        {
            "Trip Name": "Trip 43",
            "Preference Rating": 2
        },
        {
            "Trip Name": "Trip 44",
            "Preference Rating": 1
        },
        {
            "Trip Name": "Trip 45",
            "Preference Rating": 3
        },
        {
            "Trip Name": "Trip 46",
            "Preference Rating": 0
        },
        {
            "Trip Name": "Trip 47",
            "Preference Rating": 1
        },
        {
            "Trip Name": "Trip 48",
            "Preference Rating": 2
        },
        {
            "Trip Name": "Trip 49",
            "Preference Rating": 1
        },
        {
            "Trip Name": "Trip 50",
            "Preference Rating": 5
        },
        {
            "Trip Name": "Trip 51",
            "Preference Rating": 2
        },
        {
            "Trip Name": "Trip 52",
            "Preference Rating": 1
        },
        {
            "Trip Name": "Trip 53",
            "Preference Rating": 5
        },
        {
            "Trip Name": "Trip 54",
            "Preference Rating": 0
        },
        {
            "Trip Name": "Trip 55",
            "Preference Rating": 0
        },
        {
            "Trip Name": "Trip 56",
            "Preference Rating": 0
        },
        {
            "Trip Name": "Trip 57",
            "Preference Rating": 0
        }
    ],
    "sheet4_prefs": [
        {
            "TRiP Leader Name": "Rachel",
            "UFID": 12345678,
            "Semesters Left": 2,
            "Satisfaction Rating": 9,
            "Number of trips assigned last semester": 2,
            "Trips Dropped": 1,
            "Trips Picked Up": 2,
            "Categories interested in becoming a lead guide": [
                "Overnight",
                "Biking",
                "Spelunking"
            ],
            "Preferred Leaders to lead with": [
                "Dave",
                "John"
            ]
        }
    ]
}